causalinfo/__init__.py
causalinfo/equations.py
causalinfo/graph.py
causalinfo/measure.py
causalinfo/payoff.py
causalinfo/probability.py
causalinfo/util.py
causalinfo-1.1.0.dist-info/DESCRIPTION.rst
causalinfo-1.1.0.dist-info/METADATA
causalinfo-1.1.0.dist-info/RECORD
causalinfo-1.1.0.dist-info/WHEEL
causalinfo-1.1.0.dist-info/metadata.json
causalinfo-1.1.0.dist-info/top_level.txt
tests/__init__.py
tests/test_causalinfo.py
tests/test_measure.py
tests/test_probability.py
