Metadata-Version: 2.0
Name: causalinfo
Version: 1.1.0
Summary: Information Measures on Causal Graphs.
Home-page: https://github/brettc/causalinfo/
Author: Brett Calcott
Author-email: brett.calcott@gmail.com
License: MIT
Keywords: causal,information,network
Platform: UNKNOWN
Classifier: Development Status :: 4 - Beta
Classifier: Intended Audience :: Science/Research
Classifier: Natural Language :: English
Classifier: License :: OSI Approved :: MIT License
Classifier: Operating System :: OS Independent
Classifier: Programming Language :: Python
Classifier: Programming Language :: Python :: 2.7
Classifier: Topic :: Scientific/Engineering :: Mathematics
Requires-Dist: networkx
Requires-Dist: pandas
Requires-Dist: pathlib
